hot_redis/__about__.py
hot_redis/__init__.py
hot_redis/client.py
hot_redis/debounce_task.py
hot_redis/fast_dict.py
hot_redis/fast_set.py
hot_redis/multi_wait_task.py
hot_redis/py.typed
hot_redis/redis_range.py
hot_redis/tests.py
hot_redis/types.py
hot_redis/unique_id.py
hot_redis/lua/atoms.lua
hot_redis/lua/bit.lua
hot_redis2-0.22.2.dist-info/METADATA
hot_redis2-0.22.2.dist-info/WHEEL
hot_redis2-0.22.2.dist-info/licenses/AUTHORS
hot_redis2-0.22.2.dist-info/licenses/LICENSE
hot_redis2-0.22.2.dist-info/RECORD
